LICENSE
README.md
README.txt
setup.py
tomcom/__init__.py
tomcom.plone.jssort.egg-info/PKG-INFO
tomcom.plone.jssort.egg-info/SOURCES.txt
tomcom.plone.jssort.egg-info/dependency_links.txt
tomcom.plone.jssort.egg-info/entry_points.txt
tomcom.plone.jssort.egg-info/namespace_packages.txt
tomcom.plone.jssort.egg-info/not-zip-safe
tomcom.plone.jssort.egg-info/requires.txt
tomcom.plone.jssort.egg-info/top_level.txt
tomcom/plone/__init__.py
tomcom/plone/jssort/__init__.py
tomcom/plone/jssort/browser.py
tomcom/plone/jssort/configure.zcml
tomcom/plone/jssort/export.py
tomcom/plone/jssort/jssort_view.pt
tomcom/plone/jssort/profiles.zcml
tomcom/plone/jssort/locales/plone.pot
tomcom/plone/jssort/locales/de/LC_MESSAGES/plone.po
tomcom/plone/jssort/profiles/default/actions.xml
tomcom/plone/jssort/resource/css/css.css
tomcom/plone/jssort/resource/js/js.js